IMDBee/__init__.py
IMDBee/model.py
IMDBee-0.1.0.dist-info/LICENSE
IMDBee-0.1.0.dist-info/METADATA
IMDBee-0.1.0.dist-info/WHEEL
IMDBee-0.1.0.dist-info/top_level.txt
IMDBee-0.1.0.dist-info/RECORD
